WordWriter/WordWriter.py
WordWriter/__init__.py
WordWriter/constants.py
WordWriter/core.py
wordwriter-4.0.4.dist-info/licenses/LICENSE
wordwriter-4.0.4.dist-info/METADATA
wordwriter-4.0.4.dist-info/WHEEL
wordwriter-4.0.4.dist-info/top_level.txt
wordwriter-4.0.4.dist-info/RECORD
